jadeui/__init__.py
jadeui/app.py
jadeui/dialog.py
jadeui/downloader.py
jadeui/events.py
jadeui/exceptions.py
jadeui/ipc.py
jadeui/notification.py
jadeui/router.py
jadeui/server.py
jadeui/utils.py
jadeui/window.py
jadeui/core/__init__.py
jadeui/core/dll.py
jadeui/core/lifecycle.py
jadeui/core/types.py
jadeui/dll/JadeView_win_arm64_static_v1.3.0/JadeView_arm64_static.dll
jadeui/templates/__init__.py
jadeui/templates/default.css
jadeui-1.3.0.dist-info/METADATA
jadeui-1.3.0.dist-info/WHEEL
jadeui-1.3.0.dist-info/entry_points.txt
jadeui-1.3.0.dist-info/RECORD
