Metadata-Version: 2.4
Name: jadeui
Version: 1.3.0
Summary: Python SDK for JadeView - Create desktop applications with WebView
Project-URL: Homepage, https://jade.run
Project-URL: Documentation, https://jade.run/python-sdk
Project-URL: Repository, https://github.com/ArcletProject/jadeui
Project-URL: Issues, https://github.com/ArcletProject/jadeui/issues
Author: JadeView Team
License: MIT
Keywords: desktop,gui,jadeui,jadeview,ui,webview
Classifier: Development Status :: 3 - Alpha
Classifier: Intended Audience :: Developers
Classifier: License :: OSI Approved :: MIT License
Classifier: Operating System :: Microsoft :: Windows
Classifier: Programming Language :: Python :: 3
Classifier: Programming Language :: Python :: 3.7
Classifier: Programming Language :: Python :: 3.8
Classifier: Programming Language :: Python :: 3.9
Classifier: Programming Language :: Python :: 3.10
Classifier: Programming Language :: Python :: 3.11
Classifier: Programming Language :: Python :: 3.12
Classifier: Programming Language :: Python :: 3.13
Classifier: Programming Language :: Python :: 3.14
Classifier: Topic :: Desktop Environment
Classifier: Topic :: Software Development :: User Interfaces
Requires-Python: >=3.7
Provides-Extra: dev
Requires-Dist: build>=1.0; extra == 'dev'
Requires-Dist: imageio; extra == 'dev'
Requires-Dist: mypy>=1.0; extra == 'dev'
Requires-Dist: pytest>=7.0; extra == 'dev'
Requires-Dist: ruff>=0.1.0; extra == 'dev'
